ndpi_demerger/__init__.py
ndpi_demerger/extract.py
ndpi_demerger-0.1.2.dist-info/LICENSE
ndpi_demerger-0.1.2.dist-info/METADATA
ndpi_demerger-0.1.2.dist-info/WHEEL
ndpi_demerger-0.1.2.dist-info/top_level.txt
ndpi_demerger-0.1.2.dist-info/RECORD
